shipyard_cli/__init__.py
shipyard_cli/config.py
shipyard_cli/errors.py
shipyard_cli/fields.py
shipyard_cli/main.py
shipyard_cli/types.py
shipyard_cli/validators.py
shipyard_cli/crane/__init__.py
shipyard_cli/crane/commands.py
shipyard_cli/crane/service.py
shipyard_cli/node/__init__.py
shipyard_cli/node/commands.py
shipyard_cli/node/model.py
shipyard_cli/node/service.py
shipyard_cli/task/__init__.py
shipyard_cli/task/commands.py
shipyard_cli/task/model.py
shipyard_cli/task/service.py
tests/crane/__init__.py
tests/crane/test_commands.py
tests/node/__init__.py
tests/node/test_commands.py
tests/task/__init__.py
tests/task/test_commands.py
shipyard_cli-0.1.0.dist-info/LICENSE
shipyard_cli-0.1.0.dist-info/METADATA
shipyard_cli-0.1.0.dist-info/WHEEL
shipyard_cli-0.1.0.dist-info/entry_points.txt
shipyard_cli-0.1.0.dist-info/top_level.txt
shipyard_cli-0.1.0.dist-info/RECORD
