Metadata-Version: 2.1
Name: shipyard-cli
Version: 0.1.0
Summary: Command-line client for the Shipyard system
Home-page: https://github.com/varrrro/shipyard-cli
Author: Víctor Vázquez
Author-email: victorvazrod@ugr.es
License: MIT
Platform: UNKNOWN
Requires-Python: >=3.6
Requires-Dist: click
Requires-Dist: marshmallow
Requires-Dist: marshmallow-dataclass
Requires-Dist: requests
Requires-Dist: bson
